loggin_abstract/__init__.py
loggin_abstract/log_status.py
main/__init__.py
main/apartment_extractor.py
sao_paulo_rent_extractor-1.0.0.dist-info/METADATA
sao_paulo_rent_extractor-1.0.0.dist-info/WHEEL
sao_paulo_rent_extractor-1.0.0.dist-info/top_level.txt
sao_paulo_rent_extractor-1.0.0.dist-info/RECORD
